Outlier_Removal_101703571/Outlier_Removal_101703571.py
Outlier_Removal_101703571/__init__.py
Outlier_Removal_101703571-0.0.1.dist-info/LICENSE.txt
Outlier_Removal_101703571-0.0.1.dist-info/METADATA
Outlier_Removal_101703571-0.0.1.dist-info/WHEEL
Outlier_Removal_101703571-0.0.1.dist-info/top_level.txt
Outlier_Removal_101703571-0.0.1.dist-info/RECORD
