Metadata-Version: 2.1
Name: Outlier-Removal-101703571
Version: 0.0.1
Summary: Python package for Outlier Removal using Row Removal method.
Home-page: UNKNOWN
Author: Sunishka Jain
Author-email: sunishkajain15@gmail.com
License: UNKNOWN
Platform: UNKNOWN
Classifier: Programming Language :: Python :: 3
Classifier: License :: OSI Approved :: MIT License
Classifier: Operating System :: OS Independent
Requires-Python: >=3.6
